odoo/addons/stock_move_line_qty_picked/README.rst
odoo/addons/stock_move_line_qty_picked/__init__.py
odoo/addons/stock_move_line_qty_picked/__manifest__.py
odoo/addons/stock_move_line_qty_picked/i18n/it.po
odoo/addons/stock_move_line_qty_picked/i18n/stock_move_line_qty_picked.pot
odoo/addons/stock_move_line_qty_picked/models/__init__.py
odoo/addons/stock_move_line_qty_picked/models/stock_move.py
odoo/addons/stock_move_line_qty_picked/models/stock_move_line.py
odoo/addons/stock_move_line_qty_picked/readme/CONTRIBUTORS.md
odoo/addons/stock_move_line_qty_picked/readme/DESCRIPTION.md
odoo/addons/stock_move_line_qty_picked/static/description/icon.png
odoo/addons/stock_move_line_qty_picked/static/description/index.html
odoo/addons/stock_move_line_qty_picked/tests/__init__.py
odoo/addons/stock_move_line_qty_picked/tests/test_stock_move_line_qty_picked.py
odoo/addons/stock_move_line_qty_picked/views/stock_move_line.xml
odoo_addon_stock_move_line_qty_picked-18.0.1.2.1.dist-info/METADATA
odoo_addon_stock_move_line_qty_picked-18.0.1.2.1.dist-info/WHEEL
odoo_addon_stock_move_line_qty_picked-18.0.1.2.1.dist-info/top_level.txt
odoo_addon_stock_move_line_qty_picked-18.0.1.2.1.dist-info/RECORD
