Metadata-Version: 2.1
Name: odoo-addon-stock_move_line_qty_picked
Version: 18.0.1.2.1
Requires-Python: >=3.10
Requires-Dist: odoo==18.0.*
Summary: Separate quantity picked from the reserved quantity
Home-page: https://github.com/OCA/stock-logistics-workflow
License: AGPL-3
Author: Camptocamp, BCIM, Odoo Community Association (OCA)
Author-email: support@odoo-community.org
Classifier: Programming Language :: Python
Classifier: Framework :: Odoo
Classifier: Framework :: Odoo :: 18.0
Classifier: License :: OSI Approved :: GNU Affero General Public License v3
Classifier: Development Status :: 4 - Beta
